pygpcca/__init__.py
pygpcca/_gpcca.py
pygpcca/_sort_real_schur.py
pygpcca/_sorted_schur.py
pygpcca/utils/__init__.py
pygpcca/utils/_checks.py
pygpcca/utils/_constants.py
pygpcca/utils/_docs.py
pygpcca/utils/_utils.py
tests/__init__.py
tests/conftest.py
tests/test_gpcca.py
tests/test_stat_dist.py
tests/test_utils.py
pygpcca-1.0.4.dist-info/LICENSE.txt
pygpcca-1.0.4.dist-info/METADATA
pygpcca-1.0.4.dist-info/WHEEL
pygpcca-1.0.4.dist-info/top_level.txt
pygpcca-1.0.4.dist-info/RECORD
