Metadata-Version: 2.1
Name: pygpcca
Version: 1.0.4
Summary: .. |PyPIdownloads| image:: https://static.pepy.tech/personalized-badge/pygpcca?period=total&units=international_system&left_color=grey&right_color=blue&left_text=pypi%20downloads
Home-page: https://github.com/msmdev/pygpcca
Download-URL: https://pypi.org/project/pygpcca/
Author: Bernhard Reuter
Author-email: bernhard-reuter@gmx.de
Maintainer: Bernhard Reuter
Maintainer-email: bernhard-reuter@gmx.de
License: LGPLv3+
Project-URL: Documentation, https://pygpcca.readthedocs.io/en/latest
Project-URL: Source Code, https://github.com/msmdev/pygpcca
Keywords: G-PCCA,GPCCA,Generalized Perron Cluster Cluster Analysis,Markov state model,Markov state modeling,Schur decomposition,Schur vectors,cellular dynamics,cellular kinetics,coarse-graining,cyclic states,metastable states,molecular dynamics,molecular kinetics,non-autonomous process,non-equilibrium system,non-reversible process,spectral clustering
Platform: Linux
Platform: MacOSX
Classifier: Development Status :: 5 - Production/Stable
Classifier: Intended Audience :: Science/Research
Classifier: Natural Language :: English
Classifier: License :: OSI Approved :: GNU Lesser General Public License v3 or later (LGPLv3+)
Classifier: Operating System :: POSIX :: Linux
Classifier: Operating System :: MacOS :: MacOS X
Classifier: Typing :: Typed
Classifier: Programming Language :: Python :: 3
Classifier: Programming Language :: Python :: 3.6
Classifier: Programming Language :: Python :: 3.7
Classifier: Programming Language :: Python :: 3.8
Classifier: Programming Language :: Python :: 3.9
Classifier: Topic :: Scientific/Engineering :: Mathematics
License-File: LICENSE.txt
Requires-Dist: docrep (>=0.3.1)
Requires-Dist: jinja2 (==3.0.3)
Requires-Dist: numpy (>=1.17.0)
Requires-Dist: scipy (>=1.5.0)
Provides-Extra: dev
Requires-Dist: pre-commit (>=2.9.0) ; extra == 'dev'
Requires-Dist: bump2version ; extra == 'dev'
Provides-Extra: docs
Requires-Dist: nbsphinx (>=0.8) ; extra == 'docs'
Requires-Dist: sphinx (==4.0.2) ; extra == 'docs'
Requires-Dist: sphinx-autodoc-annotation ; extra == 'docs'
Requires-Dist: sphinx-autodoc-typehints (>=1.10.3) ; extra == 'docs'
Requires-Dist: sphinx-copybutton ; extra == 'docs'
Requires-Dist: sphinx-last-updated-by-git ; extra == 'docs'
Requires-Dist: sphinx-rtd-theme ; extra == 'docs'
Requires-Dist: sphinxcontrib-spelling ; extra == 'docs'
Provides-Extra: slepc
Requires-Dist: mpi4py (>=3.0.3) ; extra == 'slepc'
Requires-Dist: petsc (>=3.18.0) ; extra == 'slepc'
Requires-Dist: slepc (>=3.18.0) ; extra == 'slepc'
Requires-Dist: petsc4py (>=3.18.0) ; extra == 'slepc'
Requires-Dist: slepc4py (>=3.18.0) ; extra == 'slepc'
Provides-Extra: test
Requires-Dist: tox (>=3.20.1) ; extra == 'test'
